src/multiply.v
module mult (input clk_i,
             input rst_i,
             input [7:0] a_bi,
             input [7:0] b_bi,
             input start_i,
             output busy_o,
             output reg [15:0] y_bo);
    
    // FSM states
    localparam IDLE = 1'b0;
    localparam WORK = 1'b1;
    
    // Internal registers and wires
    reg [3:0] ctr;          // Extended counter width
    wire end_step;
    wire early_exit;        // Early termination optimization
    wire [7:0] part_sum;
    wire [15:0] shifted_part_sum;
    reg [7:0] a, b;
    reg [15:0] part_res;
    reg state;
    
    // Combinational logic
    assign part_sum         = a & {8{b[ctr]}};
    assign shifted_part_sum = part_sum << ctr;
    assign end_step         = (ctr == 4'd7);
    assign early_exit       = (b == 8'd0);  // Optimization: skip if b is zero
    assign busy_o           = state;
    

    // Main sequential logic
    always @(posedge clk_i) begin
        if (rst_i) begin
            // Reset all registers
            ctr      <= 4'd0;
            part_res <= 16'd0;
            y_bo     <= 16'd0;
            a        <= 8'd0;
            b        <= 8'd0;
            state    <= IDLE;
        end 
        else begin
            case (state)
                IDLE: begin
                    if (start_i) begin
                        state <= WORK;
                        // Load input values
                        a        <= a_bi;
                        b        <= b_bi;
                        ctr      <= 4'd0;
                        part_res <= 16'd0;
                    end
                end
                
                WORK: begin
                    // Check for completion or early exit
                    if (end_step || early_exit) begin
                        state <= IDLE;
                        y_bo  <= part_res;
                    end else begin
                        // Accumulate partial result
                        part_res <= part_res + shifted_part_sum;
                        ctr      <= ctr + 4'd1;
                        end
                    end
                    
                default: begin
                        state <= IDLE;
                    end
            endcase
        end
    end
endmodule

src/cubroot.v
module cubroot (
    input clk_i,
    input rst_i,

    input [7:0] x_bi,
    input start_i,

    output busy_o,
    output reg [7:0] y_bo
);

    // FSM states
    localparam IDLE = 1'b0;
    localparam WORK = 1'b1;

    // Internal state and registers
    reg state;
    reg [7:0] x;        // Current working value
    reg [7:0] y;        // Result accumulator
    reg [7:0] m;        // Bit mask
    reg [7:0] b_temp;   // Temporary for b = y | m
    reg [7:0] y_temp;   // Temporary for y_shifted
    
    // Combinational signals for cleaner code
    wire [7:0] m_shifted;
    wire m_not_zero;
    
    // Combinational logic
    assign m_shifted = m >> 2;
    assign m_not_zero = (m != 8'd0);
    assign busy_o = state;

    // Main sequential logic with improved structure
    always @(posedge clk_i) begin
        if (rst_i) begin
            // Reset all registers to initial state
            state <= IDLE;
            x <= 8'd0;
            y <= 8'd0;
            m <= 8'd0;
            y_bo <= 8'd0;
            b_temp <= 8'd0;
            y_temp <= 8'd0;
        end else begin
            case (state)
                IDLE: begin
                    if (start_i) begin
                        // Initialize for square root calculation
                        state <= WORK;
                        x <= x_bi;
                        y <= 8'd0;
                        m <= 8'b01000000;   // Initial mask: 1 << (WIDTH-2)
                        y_bo <= 8'd0;
                    end
                end
                
                WORK: begin
                    if (m_not_zero) begin
                        // Calculate temporary values using blocking for immediate computation
                        b_temp = y | m;
                        y_temp = y >> 1;
                        
                        // Conditionally update based on comparison
                        if (x >= b_temp) begin
                            // If x >= b_temp, subtract and set bit in result
                            x <= x - b_temp;
                            y <= y_temp | m;
                        end else begin
                            // Only update y with shifted value
                            y <= y_temp;
                        end
                        
                        // Shift mask for next iteration
                        m <= m_shifted;
                    end else begin
                        // Computation complete, output final result
                        state <= IDLE;
                        y_bo <= y;
                    end
                end
                
                default: begin
                    state <= IDLE;
                end
            endcase
        end
    end

endmodule

src/cubroot_add_system.v
`include "src/cubroot.v"
`include "src/multiply.v"
module cubroot_add_system (
    input clk_i,
    input rst_i,
    input start_i,
    input [7:0] a_bi,
    input [7:0] b_bi,
    output [15:0] result,
    output done
);

    wire sqrt_busy, mult_busy;
    wire sqrt_start, mult_start;
    wire [7:0] sqrt_result;
    
    localparam [1:0] 
        IDLE = 2'b00,
        CALC_SQRT = 2'b01,
        CALC_MULT = 2'b10,
        DONE_STATE = 2'b11;
    
    reg [1:0] state;
    
    assign sqrt_start = (state == IDLE) && start_i;
    assign mult_start = (state == CALC_SQRT) && !sqrt_busy;
    assign done = (state == DONE_STATE);
    
    always @(posedge clk_i or posedge rst_i) begin
        if (rst_i) begin
            state <= IDLE;
        end else begin
            case (state)
                IDLE: begin
                    if (start_i) begin
                        state <= CALC_SQRT;
                    end
                end
                
                CALC_SQRT: begin
                    if (!sqrt_busy) begin
                        state <= CALC_MULT;
                    end
                end
                
                CALC_MULT: begin
                    if (!mult_busy) begin
                        state <= DONE_STATE;
                    end
                end
                
                DONE_STATE: begin
                    state <= IDLE;
                end
            endcase
        end
    end
    
    cubroot sqrt_inst (
        .clk_i(clk_i),
        .rst_i(rst_i),
        .x_bi(b_bi),       
        .start_i(sqrt_start),
        .busy_o(sqrt_busy),
        .y_bo(sqrt_result)
    );
    
    mult mult_inst (
        .clk_i(clk_i),
        .rst_i(rst_i),
        .a_bi(a_bi),       
        .b_bi(sqrt_result), 
        .start_i(mult_start),
        .busy_o(mult_busy),
        .y_bo(result)       
    );

endmodule

src/test_bench.v
`timescale 1ns/1ps
`include "src/cubroot_add_system.v"

module test_bench;
    reg clk = 0;
    reg rst_i = 1;
    reg start_i = 0;
    reg [7:0] a_bi = 0;
    reg [7:0] b_bi = 0;
    wire [15:0] result;
    wire done;

    cubroot_add_system DUT (
        .clk_i(clk),
        .rst_i(rst_i),
        .start_i(start_i),
        .a_bi(a_bi),
        .b_bi(b_bi),
        .result(result),
        .done(done)
    );

    // Clock period = 10ns (100 MHz)
    always #5 clk = ~clk;
    
    // Statistics counters
    integer total_sqrt_cycles = 0;
    integer total_mult_cycles = 0;
    integer total_system_cycles = 0;
    integer test_count = 0;
    integer min_sqrt_cycles = 9999;
    integer max_sqrt_cycles = 0;
    integer min_mult_cycles = 9999;
    integer max_mult_cycles = 0;

    initial begin
        $dumpfile("wave.vcd");
        $dumpvars(0, test_bench);

        $display("\n========================================");
        $display("   CUBROOT-ADD SYSTEM TIMING ANALYSIS");
        $display("   Clock Frequency: 100 MHz (10 ns period)");
        $display("========================================\n");

        rst_i = 1;
        repeat (2) @(posedge clk);
        rst_i = 0;
        @(posedge clk);

        test(8'd4,   8'd16,  16'd16,  1);   // 4 * sqrt(16) = 16
        test(8'd5,   8'd25,  16'd25,  2);   // 5 * sqrt(25) = 25
        test(8'd3,   8'd2,   16'd3,   3);   // 3 * sqrt(2) = 3
        test(8'd0,   8'd100, 16'd0,   4);   // 0 * sqrt(100) = 0
        test(8'd8,   8'd0,   16'd0,   5);   // 8 * sqrt(0) = 0
        test(8'd1,   8'd1,   16'd1,   6);   // 1 * sqrt(1) = 1
        test(8'd255, 8'd255, 16'd3825,7);   // 255 * sqrt(255) ≈ 3825
        test(8'd100, 8'd4,   16'd200, 8);   // 100 * sqrt(4) = 200
        test(8'd2,   8'd225, 16'd30,  9);   // 2 * sqrt(225) = 30
        test(8'd6,   8'd64,  16'd48,  10);  // 6 * sqrt(64) = 48

        // Print statistics
        print_statistics();

        #10 $finish;
    end

    localparam integer MAX_WAIT_CYCLES = 2000;
    localparam real CLK_PERIOD = 10.0; // 100 MHz = 10 ns period

    task test;
        input [7:0] a, b;
        input [15:0] expected;
        input integer num;
        integer sqrt_cycles, mult_cycles, total_cycles, overhead_cycles;
        real sqrt_time_ns, mult_time_ns, total_time_ns;
        begin
            a_bi = a;
            b_bi = b;
            
            @(posedge clk) start_i = 1;
            @(posedge clk) start_i = 0;

            // Count cycles in each state
            sqrt_cycles = 0;
            mult_cycles = 0;
            overhead_cycles = 0;
            total_cycles = 0;
            
            while (!done && total_cycles < MAX_WAIT_CYCLES) begin
                @(posedge clk);
                total_cycles = total_cycles + 1;
                
                // Count cycles for each phase based on FSM state
                case (DUT.state)
                    2'b01: sqrt_cycles = sqrt_cycles + 1;  // CALC_SQRT
                    2'b10: mult_cycles = mult_cycles + 1;  // CALC_MULT
                    default: overhead_cycles = overhead_cycles + 1;
                endcase
            end

            // Calculate timing in nanoseconds
            sqrt_time_ns = sqrt_cycles * CLK_PERIOD;
            mult_time_ns = mult_cycles * CLK_PERIOD;
            total_time_ns = total_cycles * CLK_PERIOD;

            // Update statistics
            if (done) begin
                test_count = test_count + 1;
                total_sqrt_cycles = total_sqrt_cycles + sqrt_cycles;
                total_mult_cycles = total_mult_cycles + mult_cycles;
                total_system_cycles = total_system_cycles + total_cycles;
                
                if (sqrt_cycles < min_sqrt_cycles) min_sqrt_cycles = sqrt_cycles;
                if (sqrt_cycles > max_sqrt_cycles) max_sqrt_cycles = sqrt_cycles;
                if (mult_cycles < min_mult_cycles) min_mult_cycles = mult_cycles;
                if (mult_cycles > max_mult_cycles) max_mult_cycles = mult_cycles;
                
                $display("Test %2d: %3d × √%-3d = %-5d (exp %-5d) | SQRT: %2d cyc (%5.1f ns) | MULT: %2d cyc (%4.1f ns) | TOTAL: %2d cyc (%5.1f ns)", 
                         num, a, b, result, expected, 
                         sqrt_cycles, sqrt_time_ns,
                         mult_cycles, mult_time_ns,
                         total_cycles, total_time_ns);
            end else begin
                $display("TIMEOUT in test %0d", num);
            end

            repeat (2) @(posedge clk);
        end
    endtask
    
    task print_statistics;
        real avg_sqrt_cycles, avg_mult_cycles, avg_total_cycles;
        real avg_sqrt_time, avg_mult_time, avg_total_time;
        begin
            avg_sqrt_cycles = total_sqrt_cycles / test_count;
            avg_mult_cycles = total_mult_cycles / test_count;
            avg_total_cycles = total_system_cycles / test_count;
            
            avg_sqrt_time = avg_sqrt_cycles * CLK_PERIOD;
            avg_mult_time = avg_mult_cycles * CLK_PERIOD;
            avg_total_time = avg_total_cycles * CLK_PERIOD;
            
            $display("\n========================================");
            $display("           TIMING STATISTICS");
            $display("========================================");
            $display("Total tests run: %0d", test_count);
            $display("");
            $display("SQRT MODULE:");
            $display("  Average: %0.2f cycles (%0.2f ns)", avg_sqrt_cycles, avg_sqrt_time);
            $display("  Min:     %0d cycles (%0.1f ns)", min_sqrt_cycles, min_sqrt_cycles * CLK_PERIOD);
            $display("  Max:     %0d cycles (%0.1f ns)", max_sqrt_cycles, max_sqrt_cycles * CLK_PERIOD);
            $display("");
            $display("MULT MODULE:");
            $display("  Average: %0.2f cycles (%0.2f ns)", avg_mult_cycles, avg_mult_time);
            $display("  Min:     %0d cycles (%0.1f ns)", min_mult_cycles, min_mult_cycles * CLK_PERIOD);
            $display("  Max:     %0d cycles (%0.1f ns)", max_mult_cycles, max_mult_cycles * CLK_PERIOD);
            $display("");
            $display("TOTAL SYSTEM:");
            $display("  Average: %0.2f cycles (%0.2f ns)", avg_total_cycles, avg_total_time);
            $display("  Total time for all tests: %0.2f ns", total_system_cycles * CLK_PERIOD);
            $display("========================================\n");
        end
    endtask

endmodule

wave.vcd
$date
	Tue Nov 11 22:22:12 2025
$end
$version
	Icarus Verilog
$end
$timescale
	1ps
$end
$scope module test_bench $end
$var wire 16 ! result [15:0] $end
$var wire 1 " done $end
$var real 1 # CLK_PERIOD $end
$var parameter 32 $ MAX_WAIT_CYCLES $end
$var reg 8 % a_bi [7:0] $end
$var reg 8 & b_bi [7:0] $end
$var reg 1 ' clk $end
$var reg 1 ( rst_i $end
$var reg 1 ) start_i $end
$var integer 32 * max_mult_cycles [31:0] $end
$var integer 32 + max_sqrt_cycles [31:0] $end
$var integer 32 , min_mult_cycles [31:0] $end
$var integer 32 - min_sqrt_cycles [31:0] $end
$var integer 32 . test_count [31:0] $end
$var integer 32 / total_mult_cycles [31:0] $end
$var integer 32 0 total_sqrt_cycles [31:0] $end
$var integer 32 1 total_system_cycles [31:0] $end
$scope module DUT $end
$var wire 8 2 a_bi [7:0] $end
$var wire 8 3 b_bi [7:0] $end
$var wire 1 ' clk_i $end
$var wire 1 4 mult_start $end
$var wire 1 ( rst_i $end
$var wire 1 5 sqrt_start $end
$var wire 1 ) start_i $end
$var wire 8 6 sqrt_result [7:0] $end
$var wire 1 7 sqrt_busy $end
$var wire 16 8 result [15:0] $end
$var wire 1 9 mult_busy $end
$var wire 1 " done $end
$var parameter 2 : CALC_MULT $end
$var parameter 2 ; CALC_SQRT $end
$var parameter 2 < DONE_STATE $end
$var parameter 2 = IDLE $end
$var reg 2 > state [1:0] $end
$scope module mult_inst $end
$var wire 8 ? a_bi [7:0] $end
$var wire 1 9 busy_o $end
$var wire 1 ' clk_i $end
$var wire 8 @ part_sum [7:0] $end
$var wire 1 ( rst_i $end
$var wire 1 4 start_i $end
$var wire 16 A shifted_part_sum [15:0] $end
$var wire 1 B end_step $end
$var wire 1 C early_exit $end
$var wire 8 D b_bi [7:0] $end
$var parameter 1 E IDLE $end
$var parameter 1 F WORK $end
$var reg 8 G a [7:0] $end
$var reg 8 H b [7:0] $end
$var reg 4 I ctr [3:0] $end
$var reg 16 J part_res [15:0] $end
$var reg 1 K state $end
$var reg 16 L y_bo [15:0] $end
$upscope $end
$scope module sqrt_inst $end
$var wire 1 ' clk_i $end
$var wire 1 ( rst_i $end
$var wire 1 5 start_i $end
$var wire 8 M x_bi [7:0] $end
$var wire 8 N m_shifted [7:0] $end
$var wire 1 O m_not_zero $end
$var wire 1 7 busy_o $end
$var parameter 1 P IDLE $end
$var parameter 1 Q WORK $end
$var reg 8 R b_temp [7:0] $end
$var reg 8 S m [7:0] $end
$var reg 1 7 state $end
$var reg 8 T x [7:0] $end
$var reg 8 U y [7:0] $end
$var reg 8 V y_bo [7:0] $end
$var reg 8 W y_temp [7:0] $end
$upscope $end
$upscope $end
$scope task print_statistics $end
$var real 1 X avg_mult_cycles $end
$var real 1 Y avg_mult_time $end
$var real 1 Z avg_sqrt_cycles $end
$var real 1 [ avg_sqrt_time $end
$var real 1 \ avg_total_cycles $end
$var real 1 ] avg_total_time $end
$upscope $end
$scope task test $end
$var reg 8 ^ a [7:0] $end
$var reg 8 _ b [7:0] $end
$var reg 16 ` expected [15:0] $end
$var integer 32 a mult_cycles [31:0] $end
$var real 1 b mult_time_ns $end
$var integer 32 c num [31:0] $end
$var integer 32 d overhead_cycles [31:0] $end
$var integer 32 e sqrt_cycles [31:0] $end
$var real 1 f sqrt_time_ns $end
$var integer 32 g total_cycles [31:0] $end
$var real 1 h total_time_ns $end
$upscope $end
$upscope $end
$enddefinitions $end
$comment Show the parameter values. $end
$dumpall
1Q
0P
1F
0E
b0 =
b11 <
b1 ;
b10 :
b11111010000 $
r10 #
$end
#0
$dumpvars
r0 h
bx g
r0 f
bx e
bx d
bx c
r0 b
bx a
bx `
bx _
bx ^
r0 ]
r0 \
r0 [
r0 Z
r0 Y
r0 X
bx W
bx V
bx U
bx T
bx S
bx R
xO
b0xxxxxx N
b0 M
bx L
xK
bx J
bx I
bx H
bx G
bx D
xC
xB
bx A
bx @
b0 ?
b0 >
x9
bx 8
x7
bx 6
05
04
b0 3
b0 2
b0 1
b0 0
b0 /
b0 .
b10011100001111 -
b10011100001111 ,
b0 +
b0 *
0)
1(
0'
b0 &
b0 %
0"
bx !
$end
#5000
b0 N
b0 @
b0 W
b0 R
b0 6
b0 D
b0 V
0O
b0 S
b0 U
b0 T
07
09
0K
1C
b0 H
b0 G
b0 !
b0 8
b0 L
b0 J
b0 A
0B
b0 I
1'
#10000
0'
#15000
0(
1'
#20000
0'
#25000
b10000 &
b10000 3
b10000 M
b100 %
b100 2
b100 ?
b1 c
b10000 `
b10000 _
b100 ^
1'
#30000
0'
#35000
15
1)
1'
#40000
0'
#45000
b10000 N
1O
b1000000 S
b10000 T
17
b1 >
05
b0 g
b0 d
b0 a
b0 e
0)
1'
#50000
0'
#55000
b100 N
b10000 S
b1000000 R
b1 e
b1 g
1'
#60000
0'
#65000
b1 N
b100 S
b10000 U
b0 T
b10 e
b10 g
b10000 R
1'
#70000
0'
#75000
b0 N
b1 S
b1000 U
b1000 W
b10100 R
b11 e
b11 g
1'
#80000
0'
#85000
0O
b0 S
b100 U
b100 e
b100 g
b100 W
b1001 R
1'
#90000
0'
#95000
14
b100 6
b100 D
b100 V
07
b101 e
b101 g
1'
#100000
0'
#105000
04
0C
b100 H
b100 G
19
1K
b10 >
b110 e
b110 g
1'
#110000
0'
#115000
b1 I
b1 a
b111 g
1'
#120000
0'
#125000
b10000 A
b100 @
b10 I
b10 a
b1000 g
1'
#130000
0'
#135000
b0 @
b0 A
b11 I
b10000 J
b11 a
b1001 g
1'
#140000
0'
#145000
b100 I
b100 a
b1010 g
1'
#150000
0'
#155000
b101 I
b101 a
b1011 g
1'
#160000
0'
#165000
b110 I
b110 a
b1100 g
1'
#170000
0'
#175000
1B
b111 I
b111 a
b1101 g
1'
#180000
0'
#185000
b10000 !
b10000 8
b10000 L
09
0K
b1000 a
b1110 g
1'
#190000
0'
#195000
1"
b11 >
b1001 a
b1111 g
1'
#200000
0'
#205000
0"
b0 >
b1001 *
b1001 ,
b110 +
b110 -
b10000 1
b1001 /
b110 0
b1 .
r160 h
r90 b
r60 f
b1 d
b10000 g
1'
#210000
0'
#215000
1'
#220000
0'
#225000
b11001 &
b11001 3
b11001 M
b101 %
b101 2
b101 ?
b10 c
b11001 `
b11001 _
b101 ^
1'
#230000
0'
#235000
15
1)
1'
#240000
0'
#245000
b10000 N
b0 6
b0 D
b0 V
1O
b1000000 S
b0 U
b11001 T
17
b1 >
05
b0 g
b0 d
b0 a
b0 e
0)
1'
#250000
0'
#255000
b100 N
b10000 S
b0 W
b1000000 R
b1 e
b1 g
1'
#260000
0'
#265000
b1 N
b100 S
b10000 U
b1001 T
b10 e
b10 g
b10000 R
1'
#270000
0'
#275000
b0 N
b1 S
b1000 U
b1000 W
b10100 R
b11 e
b11 g
1'
#280000
0'
#285000
0O
b0 S
b101 U
b0 T
b100 e
b100 g
b100 W
b1001 R
1'
#290000
0'
#295000
14
b101 6
b101 D
b101 V
07
b101 e
b101 g
1'
#300000
0'
#305000
b101 A
b101 @
04
b0 J
0B
b0 I
b101 H
b101 G
19
1K
b10 >
b110 e
b110 g
1'
#310000
0'
#315000
b0 @
b0 A
b1 I
b101 J
b1 a
b111 g
1'
#320000
0'
#325000
b10100 A
b101 @
b10 I
b10 a
b1000 g
1'
#330000
0'
#335000
b0 @
b0 A
b11 I
b11001 J
b11 a
b1001 g
1'
#340000
0'
#345000
b100 I
b100 a
b1010 g
1'
#350000
0'
#355000
b101 I
b101 a
b1011 g
1'
#360000
0'
#365000
b110 I
b110 a
b1100 g
1'
#370000
0'
#375000
1B
b111 I
b111 a
b1101 g
1'
#380000
0'
#385000
b11001 !
b11001 8
b11001 L
09
0K
b1000 a
b1110 g
1'
#390000
0'
#395000
1"
b11 >
b1001 a
b1111 g
1'
#400000
0'
#405000
0"
b0 >
b100000 1
b10010 /
b1100 0
b10 .
b1 d
b10000 g
1'
#410000
0'
#415000
1'
#420000
0'
#425000
b10 &
b10 3
b10 M
b11 %
b11 2
b11 ?
b11 c
b11 `
b10 _
b11 ^
1'
#430000
0'
#435000
15
1)
1'
#440000
0'
#445000
b10000 N
b0 6
b0 D
b0 V
1O
b1000000 S
b0 U
b10 T
17
b1 >
05
b0 g
b0 d
b0 a
b0 e
0)
1'
#450000
0'
#455000
b100 N
b10000 S
b0 W
b1000000 R
b1 e
b1 g
1'
#460000
0'
#465000
b1 N
b100 S
b10 e
b10 g
b10000 R
1'
#470000
0'
#475000
b0 N
b1 S
b100 R
b11 e
b11 g
1'
#480000
0'
#485000
0O
b0 S
b1 U
b1 T
b100 e
b100 g
b1 R
1'
#490000
0'
#495000
14
b1 6
b1 D
b1 V
07
b101 e
b101 g
1'
#500000
0'
#505000
b11 A
b11 @
04
b0 J
0B
b0 I
b1 H
b11 G
19
1K
b10 >
b110 e
b110 g
1'
#510000
0'
#515000
b0 @
b0 A
b1 I
b11 J
b1 a
b111 g
1'
#520000
0'
#525000
b10 I
b10 a
b1000 g
1'
#530000
0'
#535000
b11 I
b11 a
b1001 g
1'
#540000
0'
#545000
b100 I
b100 a
b1010 g
1'
#550000
0'
#555000
b101 I
b101 a
b1011 g
1'
#560000
0'
#565000
b110 I
b110 a
b1100 g
1'
#570000
0'
#575000
1B
b111 I
b111 a
b1101 g
1'
#580000
0'
#585000
b11 !
b11 8
b11 L
09
0K
b1000 a
b1110 g
1'
#590000
0'
#595000
1"
b11 >
b1001 a
b1111 g
1'
#600000
0'
#605000
0"
b0 >
b110000 1
b11011 /
b10010 0
b11 .
b1 d
b10000 g
1'
#610000
0'
#615000
1'
#620000
0'
#625000
b1100100 &
b1100100 3
b1100100 M
b0 %
b0 2
b0 ?
b100 c
b0 `
b1100100 _
b0 ^
1'
#630000
0'
#635000
15
1)
1'
#640000
0'
#645000
b10000 N
b0 6
b0 D
b0 V
1O
b1000000 S
b0 U
b1100100 T
17
b1 >
05
b0 g
b0 d
b0 a
b0 e
0)
1'
#650000
0'
#655000
b100 N
b10000 S
b1000000 U
b100100 T
b1000000 R
b1 e
b1 g
1'
#660000
0'
#665000
b1 N
b100 S
b100000 U
b10 e
b10 g
b100000 W
b1010000 R
1'
#670000
0'
#675000
b0 N
b1 S
b10100 U
b0 T
b10000 W
b100100 R
b11 e
b11 g
1'
#680000
0'
#685000
0O
b0 S
b1010 U
b100 e
b100 g
b1010 W
b10101 R
1'
#690000
0'
#695000
14
b1010 6
b1010 D
b1010 V
07
b101 e
b101 g
1'
#700000
0'
#705000
04
b0 J
0B
b0 I
b1010 H
b0 G
19
1K
b10 >
b110 e
b110 g
1'
#710000
0'
#715000
b1 I
b1 a
b111 g
1'
#720000
0'
#725000
b10 I
b10 a
b1000 g
1'
#730000
0'
#735000
b11 I
b11 a
b1001 g
1'
#740000
0'
#745000
b100 I
b100 a
b1010 g
1'
#750000
0'
#755000
b101 I
b101 a
b1011 g
1'
#760000
0'
#765000
b110 I
b110 a
b1100 g
1'
#770000
0'
#775000
1B
b111 I
b111 a
b1101 g
1'
#780000
0'
#785000
b0 !
b0 8
b0 L
09
0K
b1000 a
b1110 g
1'
#790000
0'
#795000
1"
b11 >
b1001 a
b1111 g
1'
#800000
0'
#805000
0"
b0 >
b1000000 1
b100100 /
b11000 0
b100 .
b1 d
b10000 g
1'
#810000
0'
#815000
1'
#820000
0'
#825000
b0 &
b0 3
b0 M
b1000 %
b1000 2
b1000 ?
b101 c
b0 _
b1000 ^
1'
#830000
0'
#835000
15
1)
1'
#840000
0'
#845000
b10000 N
b0 6
b0 D
b0 V
1O
b1000000 S
b0 U
17
b1 >
05
b0 g
b0 d
b0 a
b0 e
0)
1'
#850000
0'
#855000
b100 N
b10000 S
b0 W
b1000000 R
b1 e
b1 g
1'
#860000
0'
#865000
b1 N
b100 S
b10 e
b10 g
b10000 R
1'
#870000
0'
#875000
b0 N
b1 S
b100 R
b11 e
b11 g
1'
#880000
0'
#885000
0O
b0 S
b100 e
b100 g
b1 R
1'
#890000
0'
#895000
14
07
b101 e
b101 g
1'
#900000
0'
#905000
04
0B
b0 I
1C
b0 H
b1000 G
19
1K
b10 >
b110 e
b110 g
1'
#910000
0'
#915000
09
0K
b1 a
b111 g
1'
#920000
0'
#925000
1"
b11 >
b10 a
b1000 g
1'
#930000
0'
#935000
0"
b0 >
b10 ,
b1001001 1
b100110 /
b11110 0
b101 .
r90 h
r20 b
b1 d
b1001 g
1'
#940000
0'
#945000
1'
#950000
0'
#955000
b1 &
b1 3
b1 M
b1 %
b1 2
b1 ?
b110 c
b1 `
b1 _
b1 ^
1'
#960000
0'
#965000
15
1)
1'
#970000
0'
#975000
b10000 N
1O
b1000000 S
b1 T
17
b1 >
05
b0 g
b0 d
b0 a
b0 e
0)
1'
#980000
0'
#985000
b100 N
b10000 S
b1000000 R
b1 e
b1 g
1'
#990000
0'
#995000
b1 N
b100 S
b10 e
b10 g
b10000 R
1'
#1000000
0'
#1005000
b0 N
b1 S
b100 R
b11 e
b11 g
1'
#1010000
0'
#1015000
0O
b0 S
b1 U
b0 T
b100 e
b100 g
b1 R
1'
#1020000
0'
#1025000
14
b1 6
b1 D
b1 V
07
b101 e
b101 g
1'
#1030000
0'
#1035000
b1 A
b1 @
04
0C
b1 H
b1 G
19
1K
b10 >
b110 e
b110 g
1'
#1040000
0'
#1045000
b0 @
b0 A
b1 I
b1 J
b1 a
b111 g
1'
#1050000
0'
#1055000
b10 I
b10 a
b1000 g
1'
#1060000
0'
#1065000
b11 I
b11 a
b1001 g
1'
#1070000
0'
#1075000
b100 I
b100 a
b1010 g
1'
#1080000
0'
#1085000
b101 I
b101 a
b1011 g
1'
#1090000
0'
#1095000
b110 I
b110 a
b1100 g
1'
#1100000
0'
#1105000
1B
b111 I
b111 a
b1101 g
1'
#1110000
0'
#1115000
b1 !
b1 8
b1 L
09
0K
b1000 a
b1110 g
1'
#1120000
0'
#1125000
1"
b11 >
b1001 a
b1111 g
1'
#1130000
0'
#1135000
0"
b0 >
b1011001 1
b101111 /
b100100 0
b110 .
r160 h
r90 b
b1 d
b10000 g
1'
#1140000
0'
#1145000
1'
#1150000
0'
#1155000
b11111111 &
b11111111 3
b11111111 M
b11111111 %
b11111111 2
b11111111 ?
b111 c
b111011110001 `
b11111111 _
b11111111 ^
1'
#1160000
0'
#1165000
15
1)
1'
#1170000
0'
#1175000
b10000 N
b0 6
b0 D
b0 V
1O
b1000000 S
b0 U
b11111111 T
17
b1 >
05
b0 g
b0 d
b0 a
b0 e
0)
1'
#1180000
0'
#1185000
b100 N
b10000 S
b1000000 U
b10111111 T
b1000000 R
b1 e
b1 g
1'
#1190000
0'
#1195000
b1 N
b100 S
b110000 U
b1101111 T
b10 e
b10 g
b100000 W
b1010000 R
1'
#1200000
0'
#1205000
b0 N
b1 S
b11100 U
b111011 T
b11000 W
b110100 R
b11 e
b11 g
1'
#1210000
0'
#1215000
0O
b0 S
b1111 U
b11110 T
b100 e
b100 g
b1110 W
b11101 R
1'
#1220000
0'
#1225000
14
b1111 6
b1111 D
b1111 V
07
b101 e
b101 g
1'
#1230000
0'
#1235000
b11111111 A
b11111111 @
04
b0 J
0B
b0 I
b1111 H
b11111111 G
19
1K
b10 >
b110 e
b110 g
1'
#1240000
0'
#1245000
b111111110 A
b1 I
b11111111 J
b1 a
b111 g
1'
#1250000
0'
#1255000
b1111111100 A
b10 I
b1011111101 J
b10 a
b1000 g
1'
#1260000
0'
#1265000
b11111111000 A
b11 I
b11011111001 J
b11 a
b1001 g
1'
#1270000
0'
#1275000
b0 @
b0 A
b100 I
b111011110001 J
b100 a
b1010 g
1'
#1280000
0'
#1285000
b101 I
b101 a
b1011 g
1'
#1290000
0'
#1295000
b110 I
b110 a
b1100 g
1'
#1300000
0'
#1305000
1B
b111 I
b111 a
b1101 g
1'
#1310000
0'
#1315000
b111011110001 !
b111011110001 8
b111011110001 L
09
0K
b1000 a
b1110 g
1'
#1320000
0'
#1325000
1"
b11 >
b1001 a
b1111 g
1'
#1330000
0'
#1335000
0"
b0 >
b1101001 1
b111000 /
b101010 0
b111 .
b1 d
b10000 g
1'
#1340000
0'
#1345000
1'
#1350000
0'
#1355000
b100 &
b100 3
b100 M
b1100100 %
b1100100 2
b1100100 ?
b1000 c
b11001000 `
b100 _
b1100100 ^
1'
#1360000
0'
#1365000
15
1)
1'
#1370000
0'
#1375000
b10000 N
b0 6
b0 D
b0 V
1O
b1000000 S
b0 U
b100 T
17
b1 >
05
b0 g
b0 d
b0 a
b0 e
0)
1'
#1380000
0'
#1385000
b100 N
b10000 S
b0 W
b1000000 R
b1 e
b1 g
1'
#1390000
0'
#1395000
b1 N
b100 S
b10 e
b10 g
b10000 R
1'
#1400000
0'
#1405000
b0 N
b1 S
b100 U
b0 T
b100 R
b11 e
b11 g
1'
#1410000
0'
#1415000
0O
b0 S
b10 U
b100 e
b100 g
b10 W
b101 R
1'
#1420000
0'
#1425000
14
b10 6
b10 D
b10 V
07
b101 e
b101 g
1'
#1430000
0'
#1435000
04
b0 J
0B
b0 I
b10 H
b1100100 G
19
1K
b10 >
b110 e
b110 g
1'
#1440000
0'
#1445000
b11001000 A
b1100100 @
b1 I
b1 a
b111 g
1'
#1450000
0'
#1455000
b0 @
b0 A
b10 I
b11001000 J
b10 a
b1000 g
1'
#1460000
0'
#1465000
b11 I
b11 a
b1001 g
1'
#1470000
0'
#1475000
b100 I
b100 a
b1010 g
1'
#1480000
0'
#1485000
b101 I
b101 a
b1011 g
1'
#1490000
0'
#1495000
b110 I
b110 a
b1100 g
1'
#1500000
0'
#1505000
1B
b111 I
b111 a
b1101 g
1'
#1510000
0'
#1515000
b11001000 !
b11001000 8
b11001000 L
09
0K
b1000 a
b1110 g
1'
#1520000
0'
#1525000
1"
b11 >
b1001 a
b1111 g
1'
#1530000
0'
#1535000
0"
b0 >
b1111001 1
b1000001 /
b110000 0
b1000 .
b1 d
b10000 g
1'
#1540000
0'
#1545000
1'
#1550000
0'
#1555000
b11100001 &
b11100001 3
b11100001 M
b10 %
b10 2
b10 ?
b1001 c
b11110 `
b11100001 _
b10 ^
1'
#1560000
0'
#1565000
15
1)
1'
#1570000
0'
#1575000
b10000 N
b0 6
b0 D
b0 V
1O
b1000000 S
b0 U
b11100001 T
17
b1 >
05
b0 g
b0 d
b0 a
b0 e
0)
1'
#1580000
0'
#1585000
b100 N
b10000 S
b1000000 U
b10100001 T
b0 W
b1000000 R
b1 e
b1 g
1'
#1590000
0'
#1595000
b1 N
b100 S
b110000 U
b1010001 T
b10 e
b10 g
b100000 W
b1010000 R
1'
#1600000
0'
#1605000
b0 N
b1 S
b11100 U
b11101 T
b11000 W
b110100 R
b11 e
b11 g
1'
#1610000
0'
#1615000
0O
b0 S
b1111 U
b0 T
b100 e
b100 g
b1110 W
b11101 R
1'
#1620000
0'
#1625000
14
b1111 6
b1111 D
b1111 V
07
b101 e
b101 g
1'
#1630000
0'
#1635000
b10 A
b10 @
04
b0 J
0B
b0 I
b1111 H
b10 G
19
1K
b10 >
b110 e
b110 g
1'
#1640000
0'
#1645000
b100 A
b1 I
b10 J
b1 a
b111 g
1'
#1650000
0'
